rewire_sqlmodel/__init__.py
rewire_sqlmodel/py.typed
rewire_sqlmodel/tests.py
rewire_sqlmodel/ext/alembic_merge_dev.py
rewire_sqlmodel/ext/alembic_migrations.py
rewire_sqlmodel/ext/fastapi.py
rewire_sqlmodel/ext/alembic_template/env.py
rewire_sqlmodel/ext/alembic_template/versions/root_initial.py
rewire_sqlmodel-0.7.1.dist-info/licenses/LICENSE
rewire_sqlmodel-0.7.1.dist-info/METADATA
rewire_sqlmodel-0.7.1.dist-info/WHEEL
rewire_sqlmodel-0.7.1.dist-info/top_level.txt
rewire_sqlmodel-0.7.1.dist-info/RECORD
