Metadata-Version: 2.4
Name: rewire-sqlmodel
Version: 0.7.1
Summary: Integration of rewire and sqlmodel
Author-email: Ivan Vozhakov <gou177@bk.ru>
License: MIT License
Project-URL: Homepage, https://github.com/rewirepy/rewire-sqlmodel
Classifier: License :: OSI Approved :: MIT License
Classifier: Programming Language :: Python
Classifier: Programming Language :: Python :: 3
Requires-Python: >=3.12
License-File: LICENSE
Requires-Dist: sqlmodel>=0.0.14
Requires-Dist: rewire
Requires-Dist: sqlalchemy_utils
Provides-Extra: dev
Requires-Dist: aiosqlite; extra == "dev"
Requires-Dist: alembic; extra == "dev"
Requires-Dist: fastapi; extra == "dev"
Requires-Dist: sqlalchemy_utils; extra == "dev"
Provides-Extra: migrations
Requires-Dist: alembic; extra == "migrations"
Provides-Extra: fastapi
Requires-Dist: fastapi; extra == "fastapi"
Dynamic: license-file
